macspoof/__init__.py
macspoof/spoof.py
macspoof-1.2.dist-info/METADATA
macspoof-1.2.dist-info/WHEEL
macspoof-1.2.dist-info/entry_points.txt
macspoof-1.2.dist-info/top_level.txt
macspoof-1.2.dist-info/RECORD
