Metadata-Version: 2.1
Name: macspoof
Version: 1.2
Summary: Spoof MAC Address on a Linux PC.
Home-page: https://github.com/Anish-M-code/macspoof
Author: Anish M
Author-email: aneesh25861@gmail.com
License: GPLv3
Keywords: privacy-tool,privacy,student project
Platform: UNKNOWN
Classifier: Development Status :: 5 - Production/Stable
Classifier: Intended Audience :: Developers
Classifier: Topic :: Software Development
Classifier: License :: OSI Approved :: GNU General Public License v3 (GPLv3)
Classifier: Programming Language :: Python :: 3
Classifier: Intended Audience :: Developers
Classifier: Intended Audience :: Education
